[
    {
        "platform_data": {
            "tasks": [
                {
                    "id": 22,
                    "job_number": 1021,
                    "sequence_number": 1,
                    "type": "PROCESS",
                    "state": "PENDING_FOR_TRANSIT",
                    "from_location": "F1",
                    "to_location": "M3",
                    "parameter": 7
                },
                {
                    "id": 23,
                    "job_number": 1022,
                    "sequence_number": 1,
                    "type": "TRANSFER",
                    "state": "PENDING_FOR_TRANSIT",
                    "from_location": "M3",
                    "to_location": "F3",
                    "parameter": 10
                },
                {
                    "id": 24,
                    "job_number": 1023,
                    "sequence_number": 1,
                    "type": "TRANSFER",
                    "state": "PENDING_FOR_TRANSIT",
                    "from_location": "M3",
                    "to_location": "M6",
                    "parameter": 7
                }
            ],
            "platform_state": "MAINTENANCE",
            "feeder_machines": [
                {
                    "id": "F1",
                    "current_state": "FEEDING_PART",
                    "target_state": "RDY"
                },
                {
                    "id": "F2",
                    "current_state": "MAINTENANCE",
                    "target_state": "MAINTENANCE"
                },
                {
                    "id": "F3",
                    "current_state": "MAINTENANCE",
                    "target_state": "MAINTENANCE"
                },
                {
                    "id": "F4",
                    "current_state": "MAINTENANCE",
                    "target_state": "MAINTENANCE"
                }
            ],
            "buffer_area": {
                "buffer_area_id": "B-004",
                "buffer_area_state": "FULL",
                "buffer_slots": [
                    {
                        "buffer_area_state": "SLOT_1",
                        "buffer_slot_occupied": "FALSE"
                    },
                    {
                        "buffer_area_state": "SLOT_2",
                        "buffer_slot_occupied": "FALSE"
                    },
                    {
                        "buffer_area_state": "SLOT_3",
                        "buffer_slot_occupied": "TRUE"
                    },
                    {
                        "buffer_area_state": "SLOT_4",
                        "buffer_slot_occupied": "TRUE"
                    },
                    {
                        "buffer_area_state": "SLOT_5",
                        "buffer_slot_occupied": "FALSE"
                    },
                    {
                        "buffer_area_state": "SLOT_6",
                        "buffer_slot_occupied": "TRUE"
                    }
                ]
            },
            "machines": [
                {
                    "id": "M1",
                    "state": "MAINTENANCE",
                    "progress_counter": 2
                },
                {
                    "id": "M2",
                    "state": "MAINTENANCE",
                    "progress_counter": 33
                },
                {
                    "id": "M3",
                    "state": "MAINTENANCE",
                    "progress_counter": 78
                },
                {
                    "id": "M4",
                    "state": "MAINTENANCE",
                    "progress_counter": 13
                },
                {
                    "id": "M5",
                    "state": "MAINTENANCE",
                    "progress_counter": 0
                },
                {
                    "id": "M6",
                    "state": "MAINTENANCE",
                    "progress_counter": 53
                }
            ],
            "logistics": {
                "current_task": {
                    "id": 25,
                    "job_number": 1024,
                    "sequence_number": 2,
                    "type": "TRANSFER",
                    "state": "IN_PROGRESS",
                    "from_location": "M5",
                    "to_location": "F4",
                    "parameter": 2
                },
                "previous_task": {
                    "id": 26,
                    "job_number": 1025,
                    "sequence_number": 0,
                    "type": "PROCESS",
                    "state": "COMPLETED",
                    "from_location": "M5",
                    "to_location": "M2",
                    "parameter": 10
                }
            }
        },
        "confirmed_schedule": null,
        "timestamp": "2024-09-28 19:33:45.248904"
    },
    {
        "platform_data": {
            "tasks": [
                {
                    "id": 27,
                    "job_number": 1026,
                    "sequence_number": 1,
                    "type": "TRANSFER",
                    "state": "PENDING_FOR_TRANSIT",
                    "from_location": "M6",
                    "to_location": "M2",
                    "parameter": 10
                },
                {
                    "id": 28,
                    "job_number": 1027,
                    "sequence_number": 5,
                    "type": "PROCESS",
                    "state": "PENDING_FOR_TRANSIT",
                    "from_location": "M4",
                    "to_location": "F4",
                    "parameter": 4
                },
                {
                    "id": 29,
                    "job_number": 1028,
                    "sequence_number": 5,
                    "type": "TRANSFER",
                    "state": "PENDING_FOR_TRANSIT",
                    "from_location": "F2",
                    "to_location": "M6",
                    "parameter": 9
                }
            ],
            "platform_state": "MAINTENANCE",
            "feeder_machines": [
                {
                    "id": "F1",
                    "current_state": "RDY",
                    "target_state": "RDY"
                },
                {
                    "id": "F2",
                    "current_state": "FAILURE",
                    "target_state": "FAILURE"
                },
                {
                    "id": "F3",
                    "current_state": "FEEDING_PART",
                    "target_state": "RDY"
                },
                {
                    "id": "F4",
                    "current_state": "RDY",
                    "target_state": "RDY"
                }
            ],
            "buffer_area": {
                "buffer_area_id": "B-004",
                "buffer_area_state": "IDLE",
                "buffer_slots": [
                    {
                        "buffer_area_state": "SLOT_1",
                        "buffer_slot_occupied": "TRUE"
                    },
                    {
                        "buffer_area_state": "SLOT_2",
                        "buffer_slot_occupied": "TRUE"
                    },
                    {
                        "buffer_area_state": "SLOT_3",
                        "buffer_slot_occupied": "FALSE"
                    },
                    {
                        "buffer_area_state": "SLOT_4",
                        "buffer_slot_occupied": "FALSE"
                    },
                    {
                        "buffer_area_state": "SLOT_5",
                        "buffer_slot_occupied": "TRUE"
                    },
                    {
                        "buffer_area_state": "SLOT_6",
                        "buffer_slot_occupied": "TRUE"
                    }
                ]
            },
            "machines": [
                {
                    "id": "M1",
                    "state": "MAINTENANCE",
                    "progress_counter": 1
                },
                {
                    "id": "M2",
                    "state": "MAINTENANCE",
                    "progress_counter": 91
                },
                {
                    "id": "M3",
                    "state": "MAINTENANCE",
                    "progress_counter": 100
                },
                {
                    "id": "M4",
                    "state": "MAINTENANCE",
                    "progress_counter": 26
                },
                {
                    "id": "M5",
                    "state": "MAINTENANCE",
                    "progress_counter": 59
                },
                {
                    "id": "M6",
                    "state": "MAINTENANCE",
                    "progress_counter": 0
                }
            ],
            "logistics": {
                "current_task": {
                    "id": 30,
                    "job_number": 1029,
                    "sequence_number": 2,
                    "type": "PROCESS",
                    "state": "COMPLETED",
                    "from_location": "M3",
                    "to_location": "M2",
                    "parameter": 1
                },
                "previous_task": {
                    "id": 31,
                    "job_number": 1030,
                    "sequence_number": 0,
                    "type": "TRANSFER",
                    "state": "IN_PROGRESS",
                    "from_location": "M5",
                    "to_location": "M5",
                    "parameter": 4
                }
            }
        },
        "confirmed_schedule": null,
        "timestamp": "2024-09-28 20:05:45.248904"
    },
    {
        "platform_data": {
            "tasks": [
                {
                    "id": 32,
                    "job_number": 1031,
                    "sequence_number": 1,
                    "type": "PROCESS",
                    "state": "PENDING_FOR_TRANSIT",
                    "from_location": "F3",
                    "to_location": "M2",
                    "parameter": 2
                },
                {
                    "id": 33,
                    "job_number": 1032,
                    "sequence_number": 4,
                    "type": "PROCESS",
                    "state": "PENDING_FOR_TRANSIT",
                    "from_location": "M3",
                    "to_location": "F4",
                    "parameter": 4
                },
                {
                    "id": 34,
                    "job_number": 1033,
                    "sequence_number": 5,
                    "type": "TRANSFER",
                    "state": "PENDING_FOR_TRANSIT",
                    "from_location": "M4",
                    "to_location": "M4",
                    "parameter": 1
                },
                {
                    "id": 35,
                    "job_number": 1034,
                    "sequence_number": 2,
                    "type": "PROCESS",
                    "state": "PENDING_FOR_TRANSIT",
                    "from_location": "M2",
                    "to_location": "M3",
                    "parameter": 6
                }
            ],
            "platform_state": "MAINTENANCE",
            "feeder_machines": [
                {
                    "id": "F1",
                    "current_state": "RDY",
                    "target_state": "RDY"
                },
                {
                    "id": "F2",
                    "current_state": "MAINTENANCE",
                    "target_state": "MAINTENANCE"
                },
                {
                    "id": "F3",
                    "current_state": "MAINTENANCE",
                    "target_state": "MAINTENANCE"
                },
                {
                    "id": "F4",
                    "current_state": "RDY",
                    "target_state": "RDY"
                }
            ],
            "buffer_area": {
                "buffer_area_id": "B-004",
                "buffer_area_state": "FULL",
                "buffer_slots": [
                    {
                        "buffer_area_state": "SLOT_1",
                        "buffer_slot_occupied": "TRUE"
                    },
                    {
                        "buffer_area_state": "SLOT_2",
                        "buffer_slot_occupied": "FALSE"
                    },
                    {
                        "buffer_area_state": "SLOT_3",
                        "buffer_slot_occupied": "TRUE"
                    },
                    {
                        "buffer_area_state": "SLOT_4",
                        "buffer_slot_occupied": "FALSE"
                    },
                    {
                        "buffer_area_state": "SLOT_5",
                        "buffer_slot_occupied": "FALSE"
                    },
                    {
                        "buffer_area_state": "SLOT_6",
                        "buffer_slot_occupied": "TRUE"
                    }
                ]
            },
            "machines": [
                {
                    "id": "M1",
                    "state": "MAINTENANCE",
                    "progress_counter": 3
                },
                {
                    "id": "M2",
                    "state": "MAINTENANCE",
                    "progress_counter": 42
                },
                {
                    "id": "M3",
                    "state": "MAINTENANCE",
                    "progress_counter": 89
                },
                {
                    "id": "M4",
                    "state": "MAINTENANCE",
                    "progress_counter": 94
                },
                {
                    "id": "M5",
                    "state": "MAINTENANCE",
                    "progress_counter": 48
                },
                {
                    "id": "M6",
                    "state": "MAINTENANCE",
                    "progress_counter": 82
                }
            ],
            "logistics": {
                "current_task": {
                    "id": 36,
                    "job_number": 1035,
                    "sequence_number": 0,
                    "type": "TRANSFER",
                    "state": "COMPLETED",
                    "from_location": "F1",
                    "to_location": "M6",
                    "parameter": 7
                },
                "previous_task": {
                    "id": 37,
                    "job_number": 1036,
                    "sequence_number": 5,
                    "type": "PROCESS",
                    "state": "COMPLETED",
                    "from_location": "F3",
                    "to_location": "M5",
                    "parameter": 8
                }
            }
        },
        "confirmed_schedule": null,
        "timestamp": "2024-09-28 20:06:45.248904"
    },
    {
        "platform_data": {
            "tasks": [
                {
                    "id": 38,
                    "job_number": 1037,
                    "sequence_number": 0,
                    "type": "TRANSFER",
                    "state": "COMPLETED",
                    "from_location": "M6",
                    "to_location": "F1",
                    "parameter": 9
                },
                {
                    "id": 39,
                    "job_number": 1038,
                    "sequence_number": 1,
                    "type": "PROCESS",
                    "state": "COMPLETED",
                    "from_location": "F4",
                    "to_location": "F4",
                    "parameter": 1
                },
                {
                    "id": 40,
                    "job_number": 1039,
                    "sequence_number": 4,
                    "type": "PROCESS",
                    "state": "PENDING_FOR_TRANSIT",
                    "from_location": "M3",
                    "to_location": "F4",
                    "parameter": 2
                },
                {
                    "id": 41,
                    "job_number": 1040,
                    "sequence_number": 3,
                    "type": "PROCESS",
                    "state": "PENDING_FOR_TRANSIT",
                    "from_location": "M5",
                    "to_location": "F4",
                    "parameter": 6
                },
                {
                    "id": 42,
                    "job_number": 1041,
                    "sequence_number": 0,
                    "type": "TRANSFER",
                    "state": "COMPLETED",
                    "from_location": "F3",
                    "to_location": "F4",
                    "parameter": 9
                }
            ],
            "platform_state": "RUNNING",
            "feeder_machines": [
                {
                    "id": "F1",
                    "current_state": "FEEDING_PART",
                    "target_state": "RDY"
                },
                {
                    "id": "F2",
                    "current_state": "FEEDING_PART",
                    "target_state": "RDY"
                },
                {
                    "id": "F3",
                    "current_state": "FEEDING_PART",
                    "target_state": "RDY"
                },
                {
                    "id": "F4",
                    "current_state": "FEEDING_PART",
                    "target_state": "RDY"
                }
            ],
            "buffer_area": {
                "buffer_area_id": "B-004",
                "buffer_area_state": "FULL",
                "buffer_slots": [
                    {
                        "buffer_area_state": "SLOT_1",
                        "buffer_slot_occupied": "FALSE"
                    },
                    {
                        "buffer_area_state": "SLOT_2",
                        "buffer_slot_occupied": "FALSE"
                    },
                    {
                        "buffer_area_state": "SLOT_3",
                        "buffer_slot_occupied": "TRUE"
                    },
                    {
                        "buffer_area_state": "SLOT_4",
                        "buffer_slot_occupied": "TRUE"
                    },
                    {
                        "buffer_area_state": "SLOT_5",
                        "buffer_slot_occupied": "TRUE"
                    },
                    {
                        "buffer_area_state": "SLOT_6",
                        "buffer_slot_occupied": "TRUE"
                    }
                ]
            },
            "machines": [
                {
                    "id": "M1",
                    "state": "FAILURE",
                    "progress_counter": 70
                },
                {
                    "id": "M2",
                    "state": "IDLE_EMPTY",
                    "progress_counter": 16
                },
                {
                    "id": "M3",
                    "state": "FAILURE",
                    "progress_counter": 47
                },
                {
                    "id": "M4",
                    "state": "MAINTENANCE",
                    "progress_counter": 25
                },
                {
                    "id": "M5",
                    "state": "PROCESSING",
                    "progress_counter": 89
                },
                {
                    "id": "M6",
                    "state": "PROCESSING",
                    "progress_counter": 79
                }
            ],
            "logistics": {
                "current_task": {
                    "id": 43,
                    "job_number": 1042,
                    "sequence_number": 5,
                    "type": "PROCESS",
                    "state": "PENDING_FOR_TRANSIT",
                    "from_location": "M3",
                    "to_location": "M3",
                    "parameter": 2
                },
                "previous_task": {
                    "id": 44,
                    "job_number": 1043,
                    "sequence_number": 1,
                    "type": "TRANSFER",
                    "state": "IN_PROGRESS",
                    "from_location": "M3",
                    "to_location": "M6",
                    "parameter": 7
                }
            }
        },
        "confirmed_schedule": [
            {
                "id": 45,
                "job_number": 1044,
                "sequence_number": 5,
                "type": "TRANSFER",
                "state": "IN_PROGRESS",
                "from_location": "M2",
                "to_location": "M1",
                "parameter": 8
            }
        ],
        "timestamp": "2024-09-28 20:40:45.248904"
    }
]