[
    {
        "platform_data": {
            "tasks": [
                {
                    "id": 1783,
                    "job_number": 2782,
                    "sequence_number": 3,
                    "type": "TRANSFER",
                    "state": "PENDING_FOR_TRANSIT",
                    "from_location": "F3",
                    "to_location": "F2",
                    "parameter": 1
                },
                {
                    "id": 1784,
                    "job_number": 2783,
                    "sequence_number": 0,
                    "type": "PROCESS",
                    "state": "PENDING_FOR_TRANSIT",
                    "from_location": "M2",
                    "to_location": "M6",
                    "parameter": 7
                },
                {
                    "id": 1785,
                    "job_number": 2784,
                    "sequence_number": 1,
                    "type": "PROCESS",
                    "state": "PENDING_FOR_TRANSIT",
                    "from_location": "M5",
                    "to_location": "M2",
                    "parameter": 9
                }
            ],
            "platform_state": "MAINTENANCE",
            "feeder_machines": [
                {
                    "id": "F1",
                    "current_state": "FAILURE",
                    "target_state": "FAILURE"
                },
                {
                    "id": "F2",
                    "current_state": "FAILURE",
                    "target_state": "FAILURE"
                },
                {
                    "id": "F3",
                    "current_state": "RDY",
                    "target_state": "RDY"
                },
                {
                    "id": "F4",
                    "current_state": "RDY",
                    "target_state": "RDY"
                }
            ],
            "buffer_area": {
                "buffer_area_id": "B-004",
                "buffer_area_state": "PROCESSING",
                "buffer_slots": [
                    {
                        "buffer_area_state": "SLOT_1",
                        "buffer_slot_occupied": "TRUE"
                    },
                    {
                        "buffer_area_state": "SLOT_2",
                        "buffer_slot_occupied": "FALSE"
                    },
                    {
                        "buffer_area_state": "SLOT_3",
                        "buffer_slot_occupied": "FALSE"
                    },
                    {
                        "buffer_area_state": "SLOT_4",
                        "buffer_slot_occupied": "FALSE"
                    },
                    {
                        "buffer_area_state": "SLOT_5",
                        "buffer_slot_occupied": "FALSE"
                    },
                    {
                        "buffer_area_state": "SLOT_6",
                        "buffer_slot_occupied": "FALSE"
                    }
                ]
            },
            "machines": [
                {
                    "id": "M1",
                    "state": "MAINTENANCE",
                    "progress_counter": 11
                },
                {
                    "id": "M2",
                    "state": "MAINTENANCE",
                    "progress_counter": 18
                },
                {
                    "id": "M3",
                    "state": "MAINTENANCE",
                    "progress_counter": 49
                },
                {
                    "id": "M4",
                    "state": "MAINTENANCE",
                    "progress_counter": 54
                },
                {
                    "id": "M5",
                    "state": "MAINTENANCE",
                    "progress_counter": 79
                },
                {
                    "id": "M6",
                    "state": "MAINTENANCE",
                    "progress_counter": 71
                }
            ],
            "logistics": {
                "current_task": {
                    "id": 1786,
                    "job_number": 2785,
                    "sequence_number": 3,
                    "type": "TRANSFER",
                    "state": "COMPLETED",
                    "from_location": "M1",
                    "to_location": "M2",
                    "parameter": 1
                },
                "previous_task": {
                    "id": 1787,
                    "job_number": 2786,
                    "sequence_number": 2,
                    "type": "PROCESS",
                    "state": "PENDING_FOR_TRANSIT",
                    "from_location": "M4",
                    "to_location": "M5",
                    "parameter": 1
                }
            }
        },
        "confirmed_schedule": null,
        "timestamp": "2024-10-05 14:18:45.248904"
    },
    {
        "platform_data": {
            "tasks": [
                {
                    "id": 1788,
                    "job_number": 2787,
                    "sequence_number": 1,
                    "type": "TRANSFER",
                    "state": "PENDING_FOR_TRANSIT",
                    "from_location": "F4",
                    "to_location": "M5",
                    "parameter": 4
                },
                {
                    "id": 1789,
                    "job_number": 2788,
                    "sequence_number": 5,
                    "type": "PROCESS",
                    "state": "PENDING_FOR_TRANSIT",
                    "from_location": "M3",
                    "to_location": "F3",
                    "parameter": 10
                }
            ],
            "platform_state": "MAINTENANCE",
            "feeder_machines": [
                {
                    "id": "F1",
                    "current_state": "MAINTENANCE",
                    "target_state": "MAINTENANCE"
                },
                {
                    "id": "F2",
                    "current_state": "RDY",
                    "target_state": "RDY"
                },
                {
                    "id": "F3",
                    "current_state": "RDY",
                    "target_state": "RDY"
                },
                {
                    "id": "F4",
                    "current_state": "RDY",
                    "target_state": "RDY"
                }
            ],
            "buffer_area": {
                "buffer_area_id": "B-002",
                "buffer_area_state": "FULL",
                "buffer_slots": [
                    {
                        "buffer_area_state": "SLOT_1",
                        "buffer_slot_occupied": "FALSE"
                    },
                    {
                        "buffer_area_state": "SLOT_2",
                        "buffer_slot_occupied": "TRUE"
                    },
                    {
                        "buffer_area_state": "SLOT_3",
                        "buffer_slot_occupied": "TRUE"
                    },
                    {
                        "buffer_area_state": "SLOT_4",
                        "buffer_slot_occupied": "TRUE"
                    },
                    {
                        "buffer_area_state": "SLOT_5",
                        "buffer_slot_occupied": "FALSE"
                    },
                    {
                        "buffer_area_state": "SLOT_6",
                        "buffer_slot_occupied": "TRUE"
                    }
                ]
            },
            "machines": [
                {
                    "id": "M1",
                    "state": "MAINTENANCE",
                    "progress_counter": 52
                },
                {
                    "id": "M2",
                    "state": "MAINTENANCE",
                    "progress_counter": 54
                },
                {
                    "id": "M3",
                    "state": "MAINTENANCE",
                    "progress_counter": 66
                },
                {
                    "id": "M4",
                    "state": "MAINTENANCE",
                    "progress_counter": 76
                },
                {
                    "id": "M5",
                    "state": "MAINTENANCE",
                    "progress_counter": 50
                },
                {
                    "id": "M6",
                    "state": "MAINTENANCE",
                    "progress_counter": 40
                }
            ],
            "logistics": {
                "current_task": {
                    "id": 1790,
                    "job_number": 2789,
                    "sequence_number": 5,
                    "type": "PROCESS",
                    "state": "IN_PROGRESS",
                    "from_location": "F4",
                    "to_location": "M2",
                    "parameter": 9
                },
                "previous_task": {
                    "id": 1791,
                    "job_number": 2790,
                    "sequence_number": 0,
                    "type": "PROCESS",
                    "state": "IN_PROGRESS",
                    "from_location": "F1",
                    "to_location": "M2",
                    "parameter": 8
                }
            }
        },
        "confirmed_schedule": null,
        "timestamp": "2024-10-05 14:45:45.248904"
    },
    {
        "platform_data": {
            "tasks": [
                {
                    "id": 1792,
                    "job_number": 2791,
                    "sequence_number": 5,
                    "type": "TRANSFER",
                    "state": "IN_PROGRESS",
                    "from_location": "M5",
                    "to_location": "M4",
                    "parameter": 5
                },
                {
                    "id": 1793,
                    "job_number": 2792,
                    "sequence_number": 3,
                    "type": "PROCESS",
                    "state": "COMPLETED",
                    "from_location": "M5",
                    "to_location": "F3",
                    "parameter": 2
                }
            ],
            "platform_state": "STOPPED",
            "feeder_machines": [
                {
                    "id": "F1",
                    "current_state": "MAINTENANCE",
                    "target_state": "MAINTENANCE"
                },
                {
                    "id": "F2",
                    "current_state": "MAINTENANCE",
                    "target_state": "MAINTENANCE"
                },
                {
                    "id": "F3",
                    "current_state": "MAINTENANCE",
                    "target_state": "MAINTENANCE"
                },
                {
                    "id": "F4",
                    "current_state": "RDY",
                    "target_state": "RDY"
                }
            ],
            "buffer_area": {
                "buffer_area_id": "B-001",
                "buffer_area_state": "IDLE",
                "buffer_slots": [
                    {
                        "buffer_area_state": "SLOT_1",
                        "buffer_slot_occupied": "FALSE"
                    },
                    {
                        "buffer_area_state": "SLOT_2",
                        "buffer_slot_occupied": "TRUE"
                    },
                    {
                        "buffer_area_state": "SLOT_3",
                        "buffer_slot_occupied": "TRUE"
                    },
                    {
                        "buffer_area_state": "SLOT_4",
                        "buffer_slot_occupied": "TRUE"
                    },
                    {
                        "buffer_area_state": "SLOT_5",
                        "buffer_slot_occupied": "TRUE"
                    },
                    {
                        "buffer_area_state": "SLOT_6",
                        "buffer_slot_occupied": "TRUE"
                    }
                ]
            },
            "machines": [
                {
                    "id": "M1",
                    "state": "IDLE_EMPTY",
                    "progress_counter": 18
                },
                {
                    "id": "M2",
                    "state": "IDLE_EMPTY",
                    "progress_counter": 18
                },
                {
                    "id": "M3",
                    "state": "MAINTENANCE",
                    "progress_counter": 37
                },
                {
                    "id": "M4",
                    "state": "IDLE_EMPTY",
                    "progress_counter": 39
                },
                {
                    "id": "M5",
                    "state": "MAINTENANCE",
                    "progress_counter": 8
                },
                {
                    "id": "M6",
                    "state": "IDLE_FULL",
                    "progress_counter": 64
                }
            ],
            "logistics": {
                "current_task": {
                    "id": 1794,
                    "job_number": 2793,
                    "sequence_number": 1,
                    "type": "PROCESS",
                    "state": "IN_PROGRESS",
                    "from_location": "M4",
                    "to_location": "M6",
                    "parameter": 4
                },
                "previous_task": {
                    "id": 1795,
                    "job_number": 2794,
                    "sequence_number": 2,
                    "type": "TRANSFER",
                    "state": "COMPLETED",
                    "from_location": "M1",
                    "to_location": "M6",
                    "parameter": 1
                }
            }
        },
        "confirmed_schedule": null,
        "timestamp": "2024-10-05 14:48:45.248904"
    },
    {
        "platform_data": {
            "tasks": [
                {
                    "id": 1796,
                    "job_number": 2795,
                    "sequence_number": 2,
                    "type": "PROCESS",
                    "state": "COMPLETED",
                    "from_location": "F3",
                    "to_location": "M5",
                    "parameter": 3
                },
                {
                    "id": 1797,
                    "job_number": 2796,
                    "sequence_number": 4,
                    "type": "TRANSFER",
                    "state": "IN_PROGRESS",
                    "from_location": "F1",
                    "to_location": "M6",
                    "parameter": 6
                },
                {
                    "id": 1798,
                    "job_number": 2797,
                    "sequence_number": 0,
                    "type": "PROCESS",
                    "state": "PENDING_FOR_TRANSIT",
                    "from_location": "M5",
                    "to_location": "F3",
                    "parameter": 5
                },
                {
                    "id": 1799,
                    "job_number": 2798,
                    "sequence_number": 1,
                    "type": "TRANSFER",
                    "state": "PENDING_FOR_TRANSIT",
                    "from_location": "M5",
                    "to_location": "F4",
                    "parameter": 10
                }
            ],
            "platform_state": "STOPPED",
            "feeder_machines": [
                {
                    "id": "F1",
                    "current_state": "FAILURE",
                    "target_state": "FAILURE"
                },
                {
                    "id": "F2",
                    "current_state": "MAINTENANCE",
                    "target_state": "MAINTENANCE"
                },
                {
                    "id": "F3",
                    "current_state": "RDY",
                    "target_state": "RDY"
                },
                {
                    "id": "F4",
                    "current_state": "FAILURE",
                    "target_state": "FAILURE"
                }
            ],
            "buffer_area": {
                "buffer_area_id": "B-002",
                "buffer_area_state": "IDLE",
                "buffer_slots": [
                    {
                        "buffer_area_state": "SLOT_1",
                        "buffer_slot_occupied": "FALSE"
                    },
                    {
                        "buffer_area_state": "SLOT_2",
                        "buffer_slot_occupied": "TRUE"
                    },
                    {
                        "buffer_area_state": "SLOT_3",
                        "buffer_slot_occupied": "FALSE"
                    },
                    {
                        "buffer_area_state": "SLOT_4",
                        "buffer_slot_occupied": "TRUE"
                    },
                    {
                        "buffer_area_state": "SLOT_5",
                        "buffer_slot_occupied": "FALSE"
                    },
                    {
                        "buffer_area_state": "SLOT_6",
                        "buffer_slot_occupied": "TRUE"
                    }
                ]
            },
            "machines": [
                {
                    "id": "M1",
                    "state": "MAINTENANCE",
                    "progress_counter": 79
                },
                {
                    "id": "M2",
                    "state": "IDLE_FULL",
                    "progress_counter": 63
                },
                {
                    "id": "M3",
                    "state": "FAILURE",
                    "progress_counter": 95
                },
                {
                    "id": "M4",
                    "state": "PROCESSING",
                    "progress_counter": 70
                },
                {
                    "id": "M5",
                    "state": "FAILURE",
                    "progress_counter": 27
                },
                {
                    "id": "M6",
                    "state": "FAILURE",
                    "progress_counter": 93
                }
            ],
            "logistics": {
                "current_task": {
                    "id": 1800,
                    "job_number": 2799,
                    "sequence_number": 3,
                    "type": "TRANSFER",
                    "state": "COMPLETED",
                    "from_location": "M5",
                    "to_location": "M1",
                    "parameter": 6
                },
                "previous_task": {
                    "id": 1801,
                    "job_number": 2800,
                    "sequence_number": 2,
                    "type": "PROCESS",
                    "state": "PENDING_FOR_TRANSIT",
                    "from_location": "M5",
                    "to_location": "F2",
                    "parameter": 5
                }
            }
        },
        "confirmed_schedule": null,
        "timestamp": "2024-10-05 15:00:45.248904"
    }
]